django_qserializer/__init__.py
django_qserializer/serialization.py
django_qserializer/tests/__init__.py
django_qserializer/tests/test_prepare_queryset.py
django_qserializer/tests/test_serializer.py
django_qserializer/tests/testapp/__init__.py
django_qserializer/tests/testapp/models.py
django_qserializer/tests/testapp/settings.py
django_qserializer-0.2.9.dist-info/LICENSE
django_qserializer-0.2.9.dist-info/METADATA
django_qserializer-0.2.9.dist-info/WHEEL
django_qserializer-0.2.9.dist-info/top_level.txt
django_qserializer-0.2.9.dist-info/RECORD
