Metadata-Version: 2.2
Name: django_qserializer
Version: 0.2.9
Summary: Django queryset and serialization together
Home-page: https://github.com/buserbrasil/django-qserializer
Author: Iuri de Silvio
Author-email: iurisilvio@gmail.com
License: MIT
Classifier: Development Status :: 3 - Alpha
Classifier: Intended Audience :: Developers
Classifier: License :: OSI Approved :: MIT License
Classifier: Operating System :: OS Independent
Classifier: Framework :: Django
Classifier: Programming Language :: Python :: 3
Classifier: Programming Language :: Python :: 3 :: Only
Classifier: Topic :: Software Development :: Libraries :: Python Modules
License-File: LICENSE
Requires-Dist: django
Provides-Extra: test
Requires-Dist: pytest; extra == "test"
Requires-Dist: pytest-cov; extra == "test"
Requires-Dist: pytest-django; extra == "test"
Requires-Dist: pytest-flake8; extra == "test"
Requires-Dist: flake8<5; extra == "test"
Dynamic: provides-extra
Dynamic: requires-dist
